{
    "family": "",
    "taskRoleArn": "",
    "executionRoleArn": "",
    "networkMode": "awsvpc",
    "requiresCompatibilities": ["FARGATE"],
    "containerDefinitions": [
        {
            "name": "",
            "image": "",
            "cpu": 0,
            "memory": 0,
            "memoryReservation": 0,
            "portMappings": [
                {
                    "containerPort": 8000,
                    "hostPort": 8000,
                    "protocol": "tcp"
                }
            ],
            "essential": true,
            "logConfiguration": {
                "logDriver": "awslogs"
            }
        }
    ]
}
